{"CTETFParticleEffect":true,"CTETFExplosion":true,"CTETFBlood":true,"CTFTankBoss":true,"CTFBaseBoss":true,"CBossAlpha":true,"CZombie":true,"CMerasmusDancer":true,"CMerasmus":true,"CHeadlessHatman":true,"CEyeballBoss":true,"CTFWeaponSapper":true,"CTFWeaponBuilder":true,"C_TFWeaponBuilder":true,"CTFTeam":true,"CTFTauntProp":true,"CTFProjectile_Rocket":true,"CTFProjectile_Flare":true,"CTFProjectile_EnergyBall":true,"CTFProjectile_GrapplingHook":true,"CTFProjectile_HealingBolt":true,"CTFProjectile_Arrow":true,"CTFPlayerResource":true,"CTFPlayer":true,"CTFRagdoll":true,"CTEPlayerAnimEvent":true,"CTFPasstimeLogic":true,"CPasstimeBall":true,"CTFObjectiveResource":true,"CTFGlow":true,"CTEFireBullets":true,"CTFBuffBanner":true,"CTFAmmoPack":true,"CObjectTeleporter":true,"CObjectSentrygun":true,"CTFProjectile_SentryRocket":true,"CObjectSapper":true,"CObjectCartDispenser":true,"CObjectDispenser":true,"CMonsterResource":true,"CFuncRespawnRoomVisualizer":true,"CFuncRespawnRoom":true,"CFuncPasstimeGoal":true,"CFuncForceField":true,"CCaptureZone":true,"CCurrencyPack":true,"CBaseObject":true,"CTFBotHintEngineerNest":true,"CBotNPCMinion":true,"CBotNPC":true,"CRagdollPropAttached":true,"CRagdollProp":true,"NextBotCombatCharacter":true,"CWaterBullet":true,"CFuncMonitor":true,"CWorld":true,"CWaterLODControl":true,"CVGuiScreen":true,"CPropJeep":true,"CPropVehicleChoreoGeneric":true,"CTEWorldDecal":true,"CTESpriteSpray":true,"CTESprite":true,"CTESparks":true,"CTESmoke":true,"CTEShowLine":true,"CTEProjectedDecal":true,"CTEPlayerDecal":true,"CTEPhysicsProp":true,"CTEParticleSystem":true,"CTEMuzzleFlash":true,"CTELargeFunnel":true,"CTEKillPlayerAttachments":true,"CTEImpact":true,"CTEGlowSprite":true,"CTEShatterSurface":true,"CTEFootprintDecal":true,"CTEFizz":true,"CTEExplosion":true,"CTEEnergySplash":true,"CTEEffectDispatch":true,"CTEDynamicLight":true,"CTEDecal":true,"CTEClientProjectile":true,"CTEBubbleTrail":true,"CTEBubbles":true,"CTEBSPDecal":true,"CTEBreakModel":true,"CTEBloodStream":true,"CTEBloodSprite":true,"CTEBeamSpline":true,"CTEBeamRingPoint":true,"CTEBeamRing":true,"CTEBeamPoints":true,"CTEBeamLaser":true,"CTEBeamFollow":true,"CTEBeamEnts":true,"CTEBeamEntPoint":true,"CTEBaseBeam":true,"CTEArmorRicochet":true,"CTEMetalSparks":true,"CTest_ProxyToggle_Networkable":true,"CTestTraceline":true,"CTesla":true,"CTeamTrainWatcher":true,"CBaseTeamObjectiveResource":true,"CTeam":true,"CSun":true,"CSteamJet":true,"CParticlePerformanceMonitor":true,"CSpotlightEnd":true,"DustTrail":true,"CFireTrail":true,"SporeTrail":true,"SporeExplosion":true,"RocketTrail":true,"SmokeTrail":true,"CSmokeStack":true,"CSlideshowDisplay":true,"CShadowControl":true,"CSceneEntity":true,"CRopeKeyframe":true,"CRagdollManager":true,"CPropVehicleDriveable":true,"CPhysicsPropMultiplayer":true,"CPhysBoxMultiplayer":true,"CBasePropDoor":true,"CDynamicProp":true,"CPointCommentaryNode":true,"CPointCamera":true,"CPlayerResource":true,"CPlasma":true,"CPhysMagnet":true,"CPhysicsProp":true,"CPhysBox":true,"CParticleSystem":true,"ParticleSmokeGrenade":true,"CParticleFire":true,"MovieExplosion":true,"CMaterialModifyControl":true,"CLightGlow":true,"CInfoOverlayAccessor":true,"CTEGaussExplosion":true,"CFuncTrackTrain":true,"CFuncSmokeVolume":true,"CFuncRotating":true,"CFuncReflectiveGlass":true,"CFuncOccluder":true,"CFunc_LOD":true,"CTEDust":true,"CFunc_Dust":true,"CFuncConveyor":true,"CBreakableSurface":true,"CFuncAreaPortalWindow":true,"CFish":true,"CEntityFlame":true,"CFireSmoke":true,"CEnvTonemapController":true,"CEnvScreenEffect":true,"CEnvScreenOverlay":true,"CEnvProjectedTexture":true,"CEnvParticleScript":true,"CFogController":true,"CEntityParticleTrail":true,"CEntityDissolve":true,"CEnvQuadraticBeam":true,"CEmbers":true,"CEnvWind":true,"CPrecipitation":true,"CDynamicLight":true,"CColorCorrectionVolume":true,"CColorCorrection":true,"CBreakableProp":true,"CBaseTempEntity":true,"CBasePlayer":true,"CBaseFlex":true,"CBaseEntity":true,"CBaseDoor":true,"CBaseCombatCharacter":true,"CBaseAnimatingOverlay":true,"CBoneFollower":true,"CBaseAnimating":true,"CInfoLightingRelative":true,"CAI_BaseNPC":true,"CWeaponIFMSteadyCam":true,"CWeaponIFMBaseCamera":true,"CWeaponIFMBase":true,"CTFWearableLevelableItem":true,"CTFWearableDemoShield":true,"CTFWearableRobotArm":true,"CTFRobotArm":true,"CTFWrench":true,"CTFProjectile_ThrowableBreadMonster":true,"CTFProjectile_ThrowableBrick":true,"CTFProjectile_ThrowableRepel":true,"CTFProjectile_Throwable":true,"CTFThrowable":true,"CTFSyringeGun":true,"CTFKatana":true,"CTFSword":true,"CSniperDot":true,"CTFSniperRifleClassic":true,"CTFSniperRifleDecap":true,"CTFSniperRifle":true,"CTFChargedSMG":true,"CTFSMG":true,"CTFShovel":true,"CTFShotgunBuildingRescue":true,"CTFPEPBrawlerBlaster":true,"CTFSodaPopper":true,"CTFShotgun_Revenge":true,"CTFScatterGun":true,"CTFShotgun_Pyro":true,"CTFShotgun_HWG":true,"CTFShotgun_Soldier":true,"CTFShotgun":true,"CTFCrossbow":true,"CTFRocketLauncher_Mortar":true,"CTFRocketLauncher_AirStrike":true,"CTFRocketLauncher_DirectHit":true,"CTFRocketLauncher":true,"CTFRevolver":true,"CTFDRGPomson":true,"CTFRaygun":true,"CTFPistol_ScoutSecondary":true,"CTFPistol_ScoutPrimary":true,"CTFPistol_Scout":true,"CTFPistol":true,"CTFPipebombLauncher":true,"CTFWeaponPDA_Spy":true,"CTFWeaponPDA_Engineer_Destroy":true,"CTFWeaponPDA_Engineer_Build":true,"CTFWeaponPDAExpansion_Teleporter":true,"CTFWeaponPDAExpansion_Dispenser":true,"CTFWeaponPDA":true,"CPasstimeGun":true,"CTFParticleCannon":true,"CTFParachute_Secondary":true,"CTFParachute_Primary":true,"CTFParachute":true,"CTFMinigun":true,"CTFMedigunShield":true,"CWeaponMedigun":true,"CTFProjectile_MechanicalArmOrb":true,"CTFMechanicalArm":true,"CTFLunchBox_Drink":true,"CTFLunchBox":true,"CLaserDot":true,"CTFLaserPointer":true,"CTFKnife":true,"CTFProjectile_Cleaver":true,"CTFProjectile_JarMilk":true,"CTFProjectile_Jar":true,"CTFCleaver":true,"CTFJarMilk":true,"CTFJar":true,"CTFWeaponInvis":true,"CTFGrenadePipebombProjectile":true,"CTFCannon":true,"CTFGrenadeLauncher":true,"CTFGrapplingHook":true,"CTFFlareGun_Revenge":true,"CTFFlareGun":true,"CTFFlameRocket":true,"CTFFlameThrower":true,"CTFFists":true,"CTFFireAxe":true,"CTFCompoundBow":true,"CTFClub":true,"CTFBuffItem":true,"CTFStickBomb":true,"CTFBottle":true,"CTFBonesaw":true,"CTFBall_Ornament":true,"CTFStunBall":true,"CTFBat_Giftwrap":true,"CTFBat_Wood":true,"CTFBat_Fish":true,"CTFBat":true,"CTFBaseRocket":true,"CTFWeaponBaseMerasmusGrenade":true,"CTFWeaponBaseMelee":true,"CTFWeaponBaseGun":true,"CTFWeaponBaseGrenadeProj":true,"CTFWeaponBase":true,"CTFViewModel":true,"CRobotDispenser":true,"CTFRobotDestruction_Robot":true,"CTFReviveMarker":true,"CTFPumpkinBomb":true,"CTFProjectile_EnergyRing":true,"CTFBaseProjectile":true,"CBaseObjectUpgrade":true,"CMannVsMachineStats":true,"CTFRobotDestructionLogic":true,"CTFRobotDestruction_RobotGroup":true,"CTFRobotDestruction_RobotSpawn":true,"CTFPlayerDestructionLogic":true,"CPlayerDestructionDispenser":true,"CTFMinigameLogic":true,"CTFHalloweenMinigame_FallingPlatforms":true,"CTFHalloweenMinigame":true,"CTFMiniGame":true,"CTFWearableVM":true,"CTFWearable":true,"CTFPowerupBottle":true,"CTFItem":true,"CHalloweenSoulPack":true,"CTFGenericBomb":true,"CBonusRoundLogic":true,"CTFGameRulesProxy":true,"CTFDroppedWeapon":true,"CTFProjectile_SpellKartBats":true,"CTFProjectile_SpellKartOrb":true,"CTFHellZap":true,"CTFProjectile_SpellLightningOrb":true,"CTFProjectile_SpellTransposeTeleport":true,"CTFProjectile_SpellMeteorShower":true,"CTFProjectile_SpellSpawnBoss":true,"CTFProjectile_SpellMirv":true,"CTFProjectile_SpellPumpkin":true,"CTFProjectile_SpellSpawnHorde":true,"CTFProjectile_SpellSpawnZombie":true,"CTFProjectile_SpellBats":true,"CTFProjectile_SpellFireball":true,"CTFSpellBook":true,"CHightower_TeleportVortex":true,"CTeleportVortex":true,"CHalloweenGiftPickup":true,"CBonusDuckPickup":true,"CHalloweenPickup":true,"CCaptureFlagReturnIcon":true,"CCaptureFlag":true,"CBonusPack":true,"CHandleTest":true,"CTeamRoundTimer":true,"CTeamplayRoundBasedRulesProxy":true,"CSpriteTrail":true,"CSpriteOriented":true,"CSprite":true,"CPoseController":true,"CGameRulesProxy":true,"CInfoLadderDismount":true,"CFuncLadder":true,"CEnvDetailController":true,"CTFWearableItem":true,"CEconWearable":true,"CBaseAttributableItem":true,"CEconEntity":true,"CBeam":true,"CBaseViewModel":true,"CBaseProjectile":true,"CBaseParticleEntity":true,"CBaseGrenade":true,"CBaseCombatWeapon":true,"CVoteController":true,"CTEHL2MPFireBullets":true,"CHL2MPRagdoll":true,"CHL2MP_Player":true,"CWeaponCitizenSuitcase":true,"CWeaponCitizenPackage":true,"CWeaponAlyxGun":true,"CWeaponCubemap":true,"CWeaponGaussGun":true,"CWeaponAnnabelle":true,"CFlaregun":true,"CWeaponBugBait":true,"CWeaponBinoculars":true,"CWeaponCycler":true,"CCrossbowBolt":true,"CPropVehiclePrisonerPod":true,"CPropCrane":true,"CPropCannon":true,"CPropAirboat":true,"CFlare":true,"CTEConcussiveExplosion":true,"CNPC_Strider":true,"CScriptIntro":true,"CRotorWashEmitter":true,"CPropCombineBall":true,"CPlasmaBeamNode":true,"CNPC_RollerMine":true,"CNPC_Manhack":true,"CNPC_CombineGunship":true,"CNPC_AntlionGuard":true,"CInfoTeleporterCountdown":true,"CMortarShell":true,"CEnvStarfield":true,"CEnvHeadcrabCanister":true,"CAlyxEmpEffect":true,"CCorpse":true,"CCitadelEnergyCore":true,"CHL2_Player":true,"CBaseHLBludgeonWeapon":true,"CHLSelectFireMachineGun":true,"CHLMachineGun":true,"CBaseHelicopter":true,"CNPC_Barney":true,"CNPC_Barnacle":true,"AR2Explosion":true,"CTEAntlionDust":true,"CVortigauntEffectDispel":true,"CVortigauntChargeToken":true,"CNPC_Vortigaunt":true,"CPredictedViewModel":true,"CWeaponStunStick":true,"CWeaponSMG1":true,"CWeapon_SLAM":true,"CWeaponShotgun":true,"CWeaponRPG":true,"CWeaponPistol":true,"CWeaponPhysCannon":true,"CHL2MPMachineGun":true,"CBaseHL2MPCombatWeapon":true,"CBaseHL2MPBludgeonWeapon":true,"CWeaponHL2MPBase":true,"CWeaponFrag":true,"CWeaponCrowbar":true,"CWeaponCrossbow":true,"CWeaponAR2":true,"CWeapon357":true,"CHL2MPGameRulesProxy":true,"CHalfLife2Proxy":true,"CBaseHLCombatWeapon":true,"CTFVehicle":true,"CTFBaseDMPowerup":true,"CWeaponSpawner":true,"CTFUmbrella":true,"CTFTranq":true,"CTFSMG_Primary":true,"CTFRevolver_Secondary":true,"CTFNailgun":true,"CTFHunterRifle":true,"CTFHeavyArtillery":true,"CTFHammerfists":true,"CTFCrowbar":true,"CTFChainsaw":true,"CTEPlantBomb":true,"CTERadioIcon":true,"CPlantedC4":true,"CCSTeam":true,"CCSPlayerResource":true,"CCSPlayer":true,"CCSRagdoll":true,"CHostage":true,"CWeaponXM1014":true,"CWeaponUSP":true,"CWeaponUMP45":true,"CWeaponTMP":true,"CSmokeGrenade":true,"CWeaponSG552":true,"CWeaponSG550":true,"CWeaponScout":true,"CWeaponP90":true,"CWeaponP228":true,"CWeaponMP5Navy":true,"CWeaponMAC10":true,"CWeaponM4A1":true,"CWeaponM3":true,"CWeaponM249":true,"CKnife":true,"CHEGrenade":true,"CWeaponGlock":true,"CWeaponGalil":true,"CWeaponG3SG1":true,"CFlashbang":true,"CWeaponFiveSeven":true,"CWeaponFamas":true,"CWeaponElite":true,"CDEagle":true,"CWeaponCSBaseGun":true,"CWeaponCSBase":true,"CC4":true,"CBaseCSGrenade":true,"CWeaponAWP":true,"CWeaponAug":true,"CAK47":true,"CFootstepControl":true,"CCSGameRulesProxy":true,"CBaseCSGrenadeProjectile":true,"CSDKTeam_Deathmatch":true,"CSDKTeam_Red":true,"CSDKTeam_Blue":true,"CSDKTeam_Unassigned":true,"CSDKTeam":true,"CSDKPlayerResource":true,"CSDKRagdoll":true,"CSDKPlayer":true,"CSparkler":true,"CRatRaceWaypoint":true,"CBriefcaseCaptureZone":true,"CBriefcase":true,"CWeaponSDKBase":true,"CWeaponMP5K":true,"CWeaponMossberg":true,"CWeaponM1911":true,"CWeaponM16":true,"CWeaponGrenade":true,"CWeaponFAL":true,"CWeaponBrawl":true,"CWeaponBeretta":true,"CBaseSDKGrenade":true,"CAkimboM1911":true,"CAkimboBeretta":true,"CAkimboBase":true,"CWeaponSDKMelee":true,"CSDKGameRulesProxy":true,"CBaseGrenadeProjectile":true,"CDAViewModel":true,"CTFWearableRazorback":true,"CTFWearableCampaignItem":true,"CTFSlap":true,"CTFRocketPack":true,"CTFGasManager":true,"CTFProjectile_JarGas":true,"CTFJarGas":true,"CTFWeaponFlameBall":true,"CTFBreakableSign":true,"CTFBreakableMelee":true,"CTFProjectile_BallOfFire":true,"CTFPointManager":true,"CTFFlameManager":true}